{
  "TITLE": "Episode 73 - The Vixens Meet a Right-Wing Extremist (featuring Carey Wedler)",
  "NUMBER": 73,
  "DESCRIPTION": "Jessie and Maddie sit down with Carey Wedler. Carey talks about she got labeled “right wing” and her frustrations with ever changing definitions of words and how important it is to move away from labels.",
  "CONTENT": "Jessie and Maddie sit down with Carey Wedler. Carey talks about she got labeled “right wing” and her frustrations with ever changing definitions of words and how important it is to move away from labels.",
  "IMAGE": "",
  "ITUNES_IMAGE": "",
  "FILE": "vv_0073.mp3",
  "DATE": "2021-02-27T23:24:39.254Z",
  "EXPLICIT": true
}
